mkversion/__init__.py
mkversion/__main__.py
mkversion/entry.py
mkversion/utils.py
mkversion/version.py
tests/__init__.py
tests/test_entry.py
mkdocs_versioning-0.4.0.dist-info/LICENSE
mkdocs_versioning-0.4.0.dist-info/METADATA
mkdocs_versioning-0.4.0.dist-info/WHEEL
mkdocs_versioning-0.4.0.dist-info/entry_points.txt
mkdocs_versioning-0.4.0.dist-info/top_level.txt
mkdocs_versioning-0.4.0.dist-info/RECORD
