Metadata-Version: 2.1
Name: mkdocs-versioning
Version: 0.4.0
Summary: A tool that allows for versioning sites built with mkdocs
Home-page: https://github.com/zayd62/mkdocs-versioning
Author: Zayd Patel
Author-email: zayd62@gmail.com
License: UNKNOWN
Project-URL: Documentation, https://zayd62.github.io/mkdocs-versioning/
Platform: UNKNOWN
Classifier: License :: OSI Approved :: MIT License
Classifier: Topic :: Documentation
Classifier: Topic :: Text Processing
Classifier: Development Status :: 4 - Beta
Classifier: Intended Audience :: Developers
Classifier: Operating System :: OS Independent
Classifier: Programming Language :: Python :: 3.6
Classifier: Programming Language :: Python :: 3.7
Classifier: Programming Language :: Python :: Implementation :: CPython
Classifier: Programming Language :: Python :: Implementation :: PyPy
Requires-Python: >=3.6
